{"data_non_statistical":false,"goal_meta_link":"https://unstats.un.org/sdgs/metadata/files/Metadata-08-02-01.pdf","goal_meta_link_text":"United Nations Sustainable Development Goals Metadata (PDF 384 KB)","graph_title":"Grundst\u00fccke 2","graph_type":"line","indicator_number":"8.2.1","indicator_name":"Grundst\u00fccke 2","indicator_sort_order":"08-02-01","published":true,"data_show_map":true,"reporting_status":"inprogress","sdg_goal":"8","target_name":"Grundst\u00fccke 2","target_id":"8.2","un_custodian_agency":"International Labour Organization (ILO)","un_designated_tier":"1","page_content":"","national_metadata_updated_date":"2021-10-15","national_data_updated_date":"2021-03-07","national_metadata_update_url_text":"2021-10-15: see changes on GitHub","national_metadata_update_url":"https://github.com/WohnungNDS/WK_Data/commit/bf1ded1754f8c8d7e07de9fccbee8288042409b8","national_data_update_url_text":"2021-03-07: see changes on GitHub","national_data_update_url":"https://github.com/WohnungNDS/WK_Data/commit/ee07c92e317d86e6c29dbe8e672bd24cf4ddcb2c","indicator":"8.2.1"}