{
  "resources": [
    {
      "path": "data.csv",
      "name": "data",
      "profile": "tabular-data-resource",
      "scheme": "file",
      "format": "csv",
      "hashing": "md5",
      "encoding": "utf-8",
      "schema": {
        "fields": [
          {
            "name": "Year",
            "type": "integer",
            "title": "Year"
          },
          {
            "name": "Gebietseinheit",
            "type": "string",
            "constraints": {
              "enum": [
                "Niedersachsen",
                "Braunschweig",
                "Braunschweig-St",
                "Salzgitter-Stad",
                "Wolfsburg-Stadt",
                "Gifhorn",
                "Goslar",
                "Goslar-Stadt",
                "Goslar (oh. Gos",
                "Helmstedt",
                "Northeim",
                "Peine",
                "Peine-Stadt",
                "Peine (oh. Pein",
                "Wolfenbüttel",
                "Wolfenbüttel-St",
                "Wolfenbüttel (o",
                "Göttingen",
                "Göttingen-Stadt",
                "Göttingen (oh.",
                "Hannover",
                "Hannover-Region",
                "Hannover-Landes",
                "Garbsen-Stadt",
                "Langenhagen-Sta",
                "Hann.Reg.(oh.Ha",
                "Diepholz",
                "Hameln-Pyrmont",
                "Hameln-Stadt",
                "Hildesheim",
                "Hildesheim-Stad",
                "Hildesheim(oh.H",
                "Holzminden",
                "Nienburg (Weser",
                "Schaumburg",
                "Lüneburg",
                "Celle",
                "Celle-Stadt",
                "Celle (oh.Celle",
                "Cuxhaven",
                "Cuxhaven-Stadt",
                "Cuxhaven (oh. C",
                "Harburg",
                "Lüchow-Dannenbe",
                "Lüneburg-Hanses",
                "Lüneburg (oh. L",
                "Osterholz",
                "Rotenburg (Wümm",
                "Heidekreis",
                "Stade",
                "Stade-Hansestad",
                "Stade (oh.Stade",
                "Uelzen",
                "Verden",
                "Weser-Ems",
                "Delmenhorst-Sta",
                "Emden-Stadt",
                "Oldenburg(Oldb)",
                "Osnabrück-Stadt",
                "Wilhelmshaven-S",
                "Ammerland",
                "Aurich",
                "Cloppenburg",
                "Emsland",
                "Lingen (Ems)-St",
                "Emsland (oh. Li",
                "Friesland",
                "Grafschaft Bent",
                "Nordhorn-Stadt",
                "Grfsch.Bentheim",
                "Leer",
                "Oldenburg",
                "Osnabrück",
                "Melle-Stadt",
                "Osnabrück (oh.M",
                "Vechta",
                "Wesermarsch",
                "Wittmund",
                "Osnabrück Stadt",
                "Wilhelmshaven S",
                "Lingen (Ems) St",
                "Nordhorn Stadt",
                "Melle Stadt",
                "Braunschweig St",
                "Salzgitter Stad",
                "Wolfsburg Stadt",
                "Goslar Stadt",
                "Peine Stadt",
                "Wolfenbüttel St",
                "Göttingen Stadt",
                "Hannover Region",
                "Hannover Landes",
                "Garbsen Stadt",
                "Langenhagen Sta",
                "Hameln Stadt",
                "Hildesheim Stad",
                "Celle Stadt",
                "Cuxhaven Stadt",
                "Lüneburg Hanses",
                "Stade Hansestad",
                "Delmenhorst Sta",
                "Emden Stadt",
                ""
              ]
            },
            "title": "Gebietseinheit"
          },
          {
            "name": "Statistik",
            "type": "string",
            "constraints": {
              "enum": [
                "Baumaßnahmen und neue Gebäude",
                "Nutzfläche des Gebäudes (100 qm)",
                "Veranschl. Kosten des Bauwerkes (1000 Euro)",
                "Wohnungen insgesamt",
                "1 Zimmer",
                "2 Zimmer",
                "3 Zimmer",
                "4 Zimmer",
                "5 Zimmer",
                "6 Zimmer",
                "7 und mehr Zimmer",
                ""
              ]
            },
            "title": "Statistik"
          },
          {
            "name": "GeoCode",
            "type": "string",
            "title": "GeoCode"
          },
          {
            "name": "Value",
            "type": "integer",
            "title": "Value"
          }
        ]
      }
    }
  ],
  "profile": "data-package",
  "name": "9-1-1",
  "title": "Steuern und Abgaben 1 Grunderwerbsteuer und Gewerbesteuersätze"
}